LICENSE
MANIFEST.in
README.md
pyproject.toml
setup.py
nnsvs/__init__.py
nnsvs/base.py
nnsvs/discriminators.py
nnsvs/dsp.py
nnsvs/gen.py
nnsvs/logger.py
nnsvs/mdn.py
nnsvs/model.py
nnsvs/multistream.py
nnsvs/pitch.py
nnsvs/postfilters.py
nnsvs/svs.py
nnsvs/train_util.py
nnsvs/util.py
nnsvs/version.py
nnsvs.egg-info/PKG-INFO
nnsvs.egg-info/SOURCES.txt
nnsvs.egg-info/dependency_links.txt
nnsvs.egg-info/entry_points.txt
nnsvs.egg-info/requires.txt
nnsvs.egg-info/top_level.txt
nnsvs/_example_data/README.md
nnsvs/_example_data/get_over.xml
nnsvs/_example_data/haruga_kita.xml
nnsvs/_example_data/song070_f00001_063.xml
nnsvs/_example_data/yuki.xml
nnsvs/acoustic_models/__init__.py
nnsvs/acoustic_models/multistream.py
nnsvs/acoustic_models/sinsy.py
nnsvs/acoustic_models/tacotron.py
nnsvs/acoustic_models/tacotron_f0.py
nnsvs/acoustic_models/util.py
nnsvs/bin/__init__.py
nnsvs/bin/anasyn.py
nnsvs/bin/fit_scaler.py
nnsvs/bin/gen_static_features.py
nnsvs/bin/generate.py
nnsvs/bin/prepare_features.py
nnsvs/bin/prepare_static_features.py
nnsvs/bin/prepare_voc_features.py
nnsvs/bin/preprocess_normalize.py
nnsvs/bin/synthesis.py
nnsvs/bin/train.py
nnsvs/bin/train_acoustic.py
nnsvs/bin/train_postfilter.py
nnsvs/bin/conf/__init__.py
nnsvs/bin/conf/fit_scaler/__init__.py
nnsvs/bin/conf/fit_scaler/config.yaml
nnsvs/bin/conf/gen_static_features/__init__.py
nnsvs/bin/conf/gen_static_features/config.yaml
nnsvs/bin/conf/generate/__init__.py
nnsvs/bin/conf/generate/config.yaml
nnsvs/bin/conf/prepare_features/__init__.py
nnsvs/bin/conf/prepare_features/config.yaml
nnsvs/bin/conf/prepare_features/acoustic/melf0_48k.yaml
nnsvs/bin/conf/prepare_features/acoustic/static_deltadelta.yaml
nnsvs/bin/conf/prepare_features/acoustic/static_only.yaml
nnsvs/bin/conf/prepare_features/duration/defaults.yaml
nnsvs/bin/conf/prepare_features/timelag/defaults.yaml
nnsvs/bin/conf/prepare_static_features/__init__.py
nnsvs/bin/conf/prepare_static_features/config.yaml
nnsvs/bin/conf/prepare_static_features/acoustic/melf0_48k.yaml
nnsvs/bin/conf/prepare_static_features/acoustic/static_deltadelta.yaml
nnsvs/bin/conf/prepare_static_features/acoustic/static_only.yaml
