Metadata-Version: 2.1
Name: nnsvs
Version: 0.1.0
Summary: DNN-based singing voice synthesis library
Provides-Extra: dev
Provides-Extra: docs
Provides-Extra: lint
Provides-Extra: test
License-File: LICENSE
